{
    "$schema": "https://getcomposer.org/schema.json",
    "config": {
        "vendor-dir": "vendor-wp-cli"
    },
    "minimum-stability": "dev",
    "prefer-stable": true,
    "repositories": {
        "wp-cli/handbook": {
            "url": "https://github.com/wp-cli/handbook",
            "type": "git"
        }
    },
    "require": {
        "php": ">=8.0"
    },
    "require-dev": {
        "wp-cli/dist-archive-command": "*",
        "wp-cli/handbook": "dev-main",
        "wp-cli/wp-cli-bundle": "*",
        "wp-cli/wp-cli-tests": "^5"
    },
    "provide": {
        "psr/log": "3.0.2",
        "wptrt/admin-notices": "v1.0.4",
        "10up/wp_mock": "1.1.1",
        "alleyinteractive/wordpress-autoloader": "v1.1.1",
        "antecedent/patchwork": "2.2.3",
        "behat/behat": "v3.29.0",
        "behat/gherkin": "v4.17.0",
        "brianhenryie/color-logger": "3.0.1",
        "codeception/codeception": "5.2.2",
        "codeception/lib-asserts": "2.2.0",
        "codeception/lib-innerbrowser": "3.1.3",
        "codeception/lib-web": "1.0.6",
        "codeception/module-asserts": "3.0.0",
        "codeception/module-cli": "2.0.1",
        "codeception/module-db": "3.2.2",
        "codeception/module-filesystem": "3.0.1",
        "codeception/module-phpbrowser": "3.0.1",
        "codeception/module-webdriver": "3.2.2",
        "codeception/stub": "4.3.0",
        "composer/installers": "v2.3.0",
        "composer/pcre": "3.4.0",
        "composer/semver": "3.4.4",
        "composer/xdebug-handler": "3.0.5",
        "dealerdirect/phpcodesniffer-composer-installer": "v1.2.1",
        "doctrine/instantiator": "2.0.0",
        "druidfi/mysqldump-php": "1.1.1",
        "dvdoug/behat-code-coverage": "v5.3.2.1",
        "fig/log-test": "1.2.1",
        "graham-campbell/result-type": "v1.1.4",
        "guzzlehttp/guzzle": "7.13.1",
        "guzzlehttp/promises": "2.5.0",
        "guzzlehttp/psr7": "2.12.3",
        "hamcrest/hamcrest-php": "v2.1.1",
        "johnpbloch/wordpress": "7.0.1",
        "johnpbloch/wordpress-core": "7.0.1",
        "johnpbloch/wordpress-core-installer": "2.0.0",
        "kamazee/pr-filter": "1.1.1",
        "laravel/serializable-closure": "v2.0.13",
        "lucatume/wp-browser": "4.7.1",
        "mnapoli/silly": "1.10.1",
        "mockery/mockery": "1.6.12",
        "myclabs/deep-copy": "1.13.4",
        "nikic/php-parser": "v5.7.0",
        "phar-io/manifest": "2.0.4",
        "phar-io/version": "3.2.1",
        "php-di/invoker": "2.3.7",
        "php-di/php-di": "7.1.1",
        "php-stubs/wordpress-stubs": "v6.9.4",
        "php-webdriver/webdriver": "1.16.0",
        "phpcsstandards/phpcsextra": "1.5.0",
        "phpcsstandards/phpcsutils": "1.2.2",
        "phpoption/phpoption": "1.9.5",
        "phpstan/extension-installer": "1.4.3",
        "phpstan/phpstan": "2.2.5",
        "phpunit/php-code-coverage": "9.2.32",
        "phpunit/php-file-iterator": "3.0.6",
        "phpunit/php-invoker": "3.1.1",
        "phpunit/php-text-template": "2.0.4",
        "phpunit/php-timer": "5.0.3",
        "phpunit/phpcov": "8.2.1",
        "phpunit/phpunit": "9.6.34",
        "psr/container": "2.0.2",
        "psr/event-dispatcher": "1.0.0",
        "psr/http-client": "1.0.3",
        "psr/http-factory": "1.1.0",
        "psr/http-message": "2.0",
        "psy/psysh": "v0.12.24",
        "ptlis/diff-parser": "1.1.0",
        "ralouphie/getallheaders": "3.0.3",
        "rector/rector": "2.5.5",
        "sebastian/cli-parser": "1.0.2",
        "sebastian/code-unit": "1.0.8",
        "sebastian/code-unit-reverse-lookup": "2.0.3",
        "sebastian/comparator": "4.0.10",
        "sebastian/complexity": "2.0.3",
        "sebastian/diff": "4.0.6",
        "sebastian/environment": "5.1.5",
        "sebastian/exporter": "4.0.8",
        "sebastian/global-state": "5.0.8",
        "sebastian/lines-of-code": "1.0.4",
        "sebastian/object-enumerator": "4.0.4",
        "sebastian/object-reflector": "2.0.4",
        "sebastian/recursion-context": "4.0.6",
        "sebastian/resource-operations": "3.0.4",
        "sebastian/type": "3.2.1",
        "sebastian/version": "3.0.2",
        "squizlabs/php_codesniffer": "3.13.5",
        "symfony/browser-kit": "v5.4.45",
        "symfony/config": "v6.4.42",
        "symfony/console": "v6.4.42",
        "symfony/css-selector": "v6.4.34",
        "symfony/dependency-injection": "v6.4.42",
        "symfony/deprecation-contracts": "v3.7.1",
        "symfony/dom-crawler": "v5.4.52",
        "symfony/event-dispatcher": "v6.4.37",
        "symfony/event-dispatcher-contracts": "v3.7.1",
        "symfony/filesystem": "v6.4.39",
        "symfony/finder": "v6.4.42",
        "symfony/polyfill-ctype": "v1.37.0",
        "symfony/polyfill-intl-grapheme": "v1.38.1",
        "symfony/polyfill-intl-normalizer": "v1.38.0",
        "symfony/polyfill-mbstring": "v1.38.2",
        "symfony/polyfill-php80": "v1.37.0",
        "symfony/process": "v6.4.41",
        "symfony/service-contracts": "v3.7.1",
        "symfony/string": "v6.4.39",
        "symfony/translation": "v6.4.42",
        "symfony/translation-contracts": "v3.7.1",
        "symfony/var-dumper": "v6.4.42",
        "symfony/var-exporter": "v6.4.42",
        "symfony/yaml": "v6.4.42",
        "szepeviktor/phpstan-wordpress": "v2.0.3",
        "theseer/tokenizer": "1.3.1",
        "vlucas/phpdotenv": "v5.6.3",
        "wordpress/wordpress": "7.0.0",
        "wp-coding-standards/wpcs": "3.3.0",
        "wpackagist-plugin/debug-log-manager": "2.5.2",
        "wpackagist-plugin/document-generator-for-openapi": "1.1.0",
        "wpackagist-plugin/monkeyman-rewrite-analyzer": "1.0",
        "wpackagist-plugin/query-monitor": "4.0.7",
        "wpackagist-plugin/woocommerce": "10.9.4",
        "wpackagist-plugin/wp-rest-api-log": "1.7.0",
        "wpackagist-theme/twentytwenty": "3.1"
    }
}